pydantic_marshals/__init__.py
pydantic_marshals/base/__init__.py
pydantic_marshals/base/composite.py
pydantic_marshals/base/fields/__init__.py
pydantic_marshals/base/fields/base.py
pydantic_marshals/base/fields/properties.py
pydantic_marshals/base/fields/py.typed
pydantic_marshals/base/models.py
pydantic_marshals/base/py.typed
pydantic_marshals/base/type_aliases.py
pydantic_marshals/contains/__init__.py
pydantic_marshals/contains/fields/__init__.py
pydantic_marshals/contains/fields/constants.py
pydantic_marshals/contains/fields/lists.py
pydantic_marshals/contains/fields/nested.py
pydantic_marshals/contains/fields/py.typed
pydantic_marshals/contains/fields/typed.py
pydantic_marshals/contains/fields/wildcards.py
pydantic_marshals/contains/models.py
pydantic_marshals/contains/type_aliases.py
pydantic_marshals/contains/type_generators/__init__.py
pydantic_marshals/contains/type_generators/base.py
pydantic_marshals/contains/type_generators/collections.py
pydantic_marshals/mypy/__init__.py
pydantic_marshals/mypy/magic.pyi
pydantic_marshals/mypy/plugin.py
pydantic_marshals/mypy/py.typed
pydantic_marshals/py.typed
pydantic_marshals/sqlalchemy/__init__.py
pydantic_marshals/sqlalchemy/fields/__init__.py
pydantic_marshals/sqlalchemy/fields/columns.py
pydantic_marshals/sqlalchemy/fields/py.typed
pydantic_marshals/sqlalchemy/fields/relationships.py
pydantic_marshals/sqlalchemy/models.py
pydantic_marshals/sqlalchemy/py.typed
pydantic_marshals/utils.py
pydantic_marshals-0.3.18.dist-info/METADATA
pydantic_marshals-0.3.18.dist-info/WHEEL
pydantic_marshals-0.3.18.dist-info/RECORD
