Metadata-Version: 2.3
Name: pydantic-marshals
Version: 0.3.18
Summary: Library for creating partial pydantic models (automatic converters) from different mappings
Author: niqzart
Author-email: niqzart@gmail.com
Requires-Python: >=3.10,<4.0
Classifier: Programming Language :: Python :: 3
Classifier: Programming Language :: Python :: 3.10
Classifier: Programming Language :: Python :: 3.11
Classifier: Programming Language :: Python :: 3.12
Classifier: Programming Language :: Python :: 3.13
Provides-Extra: assert-contains
Provides-Extra: sqlalchemy
Requires-Dist: pydantic (>=2.0,<3.0)
Requires-Dist: sqlalchemy (>=2.0,<3.0) ; extra == "sqlalchemy"
